{
    "pageNumber": 6,
    "data": [
        {
            "id": "158700",
            "title": "ELIJAH GATES AND KAULANA APO AT KEWALO BASIN",
            "date_created": "1398292505",
            "loginId": "3",
            "tags": "",
            "description": "A fun little piece on two of our favorite Hawaiian up-and-comers. You'll definitley crack a smile over these kids (we promise). Video: PK.",
            "asset": {
                "author": "Hurley",
                "videoId": "CArfsQlM3uY",
                "hookText": "A fun little piece on two of our favorite Hawaiian up-and-comers. You'll definitley crack a smile over these kids (we promise). Video: PK.",
                "thumbnailUrl": "https:\/\/i.ytimg.com\/vi\/CArfsQlM3uY\/hqdefault.jpg",
                "mediaDuration": "111",
                "hdvFlag": 0,
                "uploadDate": 1304039996,
                "prettyDuration": "01:51"
            },
            "parentId": "158327",
            "url": "\/hurley\/elijah-gates-and-kaulana-apo-at-kewalo-basin\/158327-158700"
        },
        {
            "id": "158701",
            "title": "ROB MACHADO PRO JUNIOR: SEASIDE BEGINNINGS",
            "date_created": "1398292505",
            "loginId": "3",
            "tags": "",
            "description": "Neon wetsuits, big stickers, The Mouse and other musings from Rob as he reflects on growing up a Seaside grom. Video: PK.",
            "asset": {
                "author": "Hurley",
                "videoId": "Wol-VkWw3w0",
                "hookText": "Neon wetsuits, big stickers, The Mouse and other musings from Rob as he reflects on growing up a Seaside grom. Video: PK.",
                "thumbnailUrl": "https:\/\/i.ytimg.com\/vi\/Wol-VkWw3w0\/maxresdefault.jpg",
                "mediaDuration": "110",
                "hdvFlag": 1,
                "uploadDate": 1304039988,
                "prettyDuration": "01:50"
            },
            "parentId": "158327",
            "url": "\/hurley\/rob-machado-pro-junior-seaside-beginnings\/158327-158701"
        },
        {
            "id": "158702",
            "title": "BEHIND THE SCENES: CHAPTER FOUR",
            "date_created": "1398292505",
            "loginId": "3",
            "tags": "",
            "description": "JP tries to infiltrate The Hive to get a look at the new Phantom 4D. Video: YB.",
            "asset": {
                "author": "Hurley",
                "videoId": "eoqihLkmnZQ",
                "hookText": "JP tries to infiltrate The Hive to get a look at the new Phantom 4D. Video: YB.",
                "thumbnailUrl": "https:\/\/i.ytimg.com\/vi\/eoqihLkmnZQ\/maxresdefault.jpg",
                "mediaDuration": "174",
                "hdvFlag": 1,
                "uploadDate": 1304039402,
                "prettyDuration": "02:54"
            },
            "parentId": "158327",
            "url": "\/hurley\/behind-the-scenes-chapter-four\/158327-158702"
        },
        {
            "id": "158703",
            "title": "PHANTOM INNOVATION",
            "date_created": "1398292505",
            "loginId": "3",
            "tags": "",
            "description": "4D is here: The next dimension of innovation. Video: Francisco Magana.",
            "asset": {
                "author": "Hurley",
                "videoId": "oOQDLUhm6qY",
                "hookText": "4D is here: The next dimension of innovation. Video: Francisco Magana.",
                "thumbnailUrl": "https:\/\/i.ytimg.com\/vi\/oOQDLUhm6qY\/maxresdefault.jpg",
                "mediaDuration": "24",
                "hdvFlag": 1,
                "uploadDate": 1304039196,
                "prettyDuration": "00:24"
            },
            "parentId": "158327",
            "url": "\/hurley\/phantom-innovation\/158327-158703"
        },
        {
            "id": "158704",
            "title": "WAVE OF THE WEEK: OLIVER KURTZ",
            "date_created": "1398292505",
            "loginId": "3",
            "tags": "",
            "description": "The power and glory of Pipeline on full display. Ollie's just along for the ride. Video: Tom Aiello.",
            "asset": {
                "author": "Hurley",
                "videoId": "eCeSlT70nWU",
                "hookText": "The power and glory of Pipeline on full display. Ollie's just along for the ride. Video: Tom Aiello.",
                "thumbnailUrl": "https:\/\/i.ytimg.com\/vi\/eCeSlT70nWU\/maxresdefault.jpg",
                "mediaDuration": "30",
                "hdvFlag": 1,
                "uploadDate": 1302768175,
                "prettyDuration": "00:30"
            },
            "parentId": "158327",
            "url": "\/hurley\/wave-of-the-week-oliver-kurtz\/158327-158704"
        },
        {
            "id": "158705",
            "title": "FROM CONCEPT TO COMPLETION WITH BRANDON BOYD",
            "date_created": "1398292505",
            "loginId": "3",
            "tags": "",
            "description": "An exclusive behind-the-scenes look at the making of Brandon Boyd's first-ever mural project. Our cameras were with Brandon through the entire process to pro...",
            "asset": {
                "author": "Hurley",
                "videoId": "4DrmWSYMy4U",
                "hookText": "An exclusive behind-the-scenes look at the making of Brandon Boyd's first-ever mural project. Our cameras were with Brandon through the entire process to pro...",
                "thumbnailUrl": "https:\/\/i.ytimg.com\/vi\/4DrmWSYMy4U\/maxresdefault.jpg",
                "mediaDuration": "99",
                "hdvFlag": 1,
                "uploadDate": 1302305335,
                "prettyDuration": "01:39"
            },
            "parentId": "158327",
            "url": "\/hurley\/from-concept-to-completion-with-brandon-boyd\/158327-158705"
        },
        {
            "id": "158706",
            "title": "ROB AND BAND REHEARSE FOR UPCOMING BI-COASTAL MELALI TOUR",
            "date_created": "1398292505",
            "loginId": "3",
            "tags": "",
            "description": "Rob and the Melali Sessions Band let us into the studio as they prepare for the Melali: The Drifter Sessions tour, scheduled to kick off in Solana Beach, Cal...",
            "asset": {
                "author": "Hurley",
                "videoId": "dNKZYLq5EnI",
                "hookText": "Rob and the Melali Sessions Band let us into the studio as they prepare for the Melali: The Drifter Sessions tour, scheduled to kick off in Solana Beach, Cal...",
                "thumbnailUrl": "https:\/\/i.ytimg.com\/vi\/dNKZYLq5EnI\/maxresdefault.jpg",
                "mediaDuration": "56",
                "hdvFlag": 1,
                "uploadDate": 1302063116,
                "prettyDuration": "00:56"
            },
            "parentId": "158327",
            "url": "\/hurley\/rob-and-band-rehearse-for-upcoming-bi-coastal-melali-tour\/158327-158706"
        },
        {
            "id": "158707",
            "title": "WAVE OF THE WEEK: BRETT SIMPSON",
            "date_created": "1398292505",
            "loginId": "3",
            "tags": "",
            "description": "Brett liens into one. Did you know: The lien air gets its name from the man who invented the maneuver -- Neil Blender? Lien, not coincidentally, is Neil spel...",
            "asset": {
                "author": "Hurley",
                "videoId": "1bmf9LPia7s",
                "hookText": "Brett liens into one. Did you know: The lien air gets its name from the man who invented the maneuver -- Neil Blender? Lien, not coincidentally, is Neil spel...",
                "thumbnailUrl": "https:\/\/i.ytimg.com\/vi\/1bmf9LPia7s\/maxresdefault.jpg",
                "mediaDuration": "30",
                "hdvFlag": 1,
                "uploadDate": 1302061649,
                "prettyDuration": "00:30"
            },
            "parentId": "158327",
            "url": "\/hurley\/wave-of-the-week-brett-simpson\/158327-158707"
        },
        {
            "id": "158708",
            "title": "CHEVY DEMO DAY AT HURLEY",
            "date_created": "1398292505",
            "loginId": "3",
            "tags": "",
            "description": "We're fans of new technology around here (and no, it doesn't just have to do with boardshorts). That's why when Chevy approached us about coming to campus to...",
            "asset": {
                "author": "Hurley",
                "videoId": "jspFobZvSGs",
                "hookText": "We're fans of new technology around here (and no, it doesn't just have to do with boardshorts). That's why when Chevy approached us about coming to campus to...",
                "thumbnailUrl": "https:\/\/i.ytimg.com\/vi\/jspFobZvSGs\/maxresdefault.jpg",
                "mediaDuration": "135",
                "hdvFlag": 1,
                "uploadDate": 1302061570,
                "prettyDuration": "02:15"
            },
            "parentId": "158327",
            "url": "\/hurley\/chevy-demo-day-at-hurley\/158327-158708"
        },
        {
            "id": "158709",
            "title": "BOB BURNQUIST AND CURREN CAPLES AT THE BOWL-A-RAMA IN BONDI",
            "date_created": "1398292506",
            "loginId": "3",
            "tags": "",
            "description": "Highlights of Curren Caples and Bob Burnquist from the VANS BOWL-A-RAMA in Bondi. Video: Bruno Pasos.",
            "asset": {
                "author": "Hurley",
                "videoId": "nTkzCbGQVMg",
                "hookText": "Highlights of Curren Caples and Bob Burnquist from the VANS BOWL-A-RAMA in Bondi. Video: Bruno Pasos.",
                "thumbnailUrl": "https:\/\/i.ytimg.com\/vi\/nTkzCbGQVMg\/hqdefault.jpg",
                "mediaDuration": "272",
                "hdvFlag": 0,
                "uploadDate": 1301549722,
                "prettyDuration": "04:32"
            },
            "parentId": "158327",
            "url": "\/hurley\/bob-burnquist-and-curren-caples-at-the-bowl-a-rama-in-bondi\/158327-158709"
        },
        {
            "id": "158710",
            "title": "JOSEPH MAREINA AND JASON VANZANT",
            "date_created": "1398292506",
            "loginId": "3",
            "tags": "",
            "description": "Here's something different. A quick skate clip of Joseph Mareina and Jason Vanzant. Video: Bruno Pasos.",
            "asset": {
                "author": "Hurley",
                "videoId": "BcVj2j4Wo34",
                "hookText": "Here's something different. A quick skate clip of Joseph Mareina and Jason Vanzant. Video: Bruno Pasos.",
                "thumbnailUrl": "https:\/\/i.ytimg.com\/vi\/BcVj2j4Wo34\/hqdefault.jpg",
                "mediaDuration": "100",
                "hdvFlag": 0,
                "uploadDate": 1301549694,
                "prettyDuration": "01:40"
            },
            "parentId": "158327",
            "url": "\/hurley\/joseph-mareina-and-jason-vanzant\/158327-158710"
        },
        {
            "id": "158711",
            "title": "WAVE OF THE WEEK: EVAN GEISELMAN",
            "date_created": "1398292506",
            "loginId": "3",
            "tags": "",
            "description": "Small waves make the best ramps. Evan Geiselman proves that, sure, while pumping down the line to punt one massive air might not score points with surfing pu...",
            "asset": {
                "author": "Hurley",
                "videoId": "Epe1aZE2QdE",
                "hookText": "Small waves make the best ramps. Evan Geiselman proves that, sure, while pumping down the line to punt one massive air might not score points with surfing pu...",
                "thumbnailUrl": "https:\/\/i.ytimg.com\/vi\/Epe1aZE2QdE\/maxresdefault.jpg",
                "mediaDuration": "30",
                "hdvFlag": 1,
                "uploadDate": 1301549370,
                "prettyDuration": "00:30"
            },
            "parentId": "158327",
            "url": "\/hurley\/wave-of-the-week-evan-geiselman\/158327-158711"
        },
        {
            "id": "158712",
            "title": "DALEK ON THE COLLABORATIVE PROCESS WITH HURLEY",
            "date_created": "1398292506",
            "loginId": "3",
            "tags": "",
            "description": "Dalek explains the evolution of the partnership between he and the Hurley design team, in particular the development of his creative relationship with Ryan H...",
            "asset": {
                "author": "Hurley",
                "videoId": "zna4L-vODLU",
                "hookText": "Dalek explains the evolution of the partnership between he and the Hurley design team, in particular the development of his creative relationship with Ryan H...",
                "thumbnailUrl": "https:\/\/i.ytimg.com\/vi\/zna4L-vODLU\/maxresdefault.jpg",
                "mediaDuration": "83",
                "hdvFlag": 1,
                "uploadDate": 1301549080,
                "prettyDuration": "01:23"
            },
            "parentId": "158327",
            "url": "\/hurley\/dalek-on-the-collaborative-process-with-hurley\/158327-158712"
        },
        {
            "id": "158713",
            "title": "BEHIND THE SCENES: CHAPTER THREE",
            "date_created": "1398292506",
            "loginId": "3",
            "tags": "",
            "description": "JP raps out with the guys at the Hurley Employee Store and gets their take on the new Phantoms. Video: Mark Choiniere.",
            "asset": {
                "author": "Hurley",
                "videoId": "3J8lmZx9aSQ",
                "hookText": "JP raps out with the guys at the Hurley Employee Store and gets their take on the new Phantoms. Video: Mark Choiniere.",
                "thumbnailUrl": "https:\/\/i.ytimg.com\/vi\/3J8lmZx9aSQ\/maxresdefault.jpg",
                "mediaDuration": "140",
                "hdvFlag": 1,
                "uploadDate": 1301023548,
                "prettyDuration": "02:20"
            },
            "parentId": "158327",
            "url": "\/hurley\/behind-the-scenes-chapter-three\/158327-158713"
        },
        {
            "id": "158714",
            "title": "JON ROSE ON WAVES FOR WATER'S ROLE IN HAITI",
            "date_created": "1398292506",
            "loginId": "3",
            "tags": "",
            "description": "Jon Rose's explains what the Waves For Water mission is in Haiti. Video: Marc Choiniere.",
            "asset": {
                "author": "Hurley",
                "videoId": "dCK_SoL0Gfs",
                "hookText": "Jon Rose's explains what the Waves For Water mission is in Haiti. Video: Marc Choiniere.",
                "thumbnailUrl": "https:\/\/i.ytimg.com\/vi\/dCK_SoL0Gfs\/maxresdefault.jpg",
                "mediaDuration": "140",
                "hdvFlag": 1,
                "uploadDate": 1300841645,
                "prettyDuration": "02:20"
            },
            "parentId": "158327",
            "url": "\/hurley\/jon-rose-on-waves-for-water-s-role-in-haiti\/158327-158714"
        },
        {
            "id": "158715",
            "title": "ATHLETES: CONNER COFFIN",
            "date_created": "1398292506",
            "loginId": "3",
            "tags": "",
            "description": "Conner Coffin on balancing fear and committment in big waves. Video: Tom Aiello.",
            "asset": {
                "author": "Hurley",
                "videoId": "rSN1oD-ohn4",
                "hookText": "Conner Coffin on balancing fear and committment in big waves. Video: Tom Aiello.",
                "thumbnailUrl": "https:\/\/i.ytimg.com\/vi\/rSN1oD-ohn4\/maxresdefault.jpg",
                "mediaDuration": "53",
                "hdvFlag": 1,
                "uploadDate": 1300841128,
                "prettyDuration": "00:53"
            },
            "parentId": "158327",
            "url": "\/hurley\/athletes-conner-coffin\/158327-158715"
        },
        {
            "id": "158716",
            "title": "BRETT SIMPSON'S NOT-SO-STANDARD THREE TO THE BEACH",
            "date_created": "1398292506",
            "loginId": "3",
            "tags": "",
            "description": "For Brett, it's as easy as one-two-three. Video: Tom Aiello.",
            "asset": {
                "author": "Hurley",
                "videoId": "lpg8Sp9RWi0",
                "hookText": "For Brett, it's as easy as one-two-three. Video: Tom Aiello.",
                "thumbnailUrl": "https:\/\/i.ytimg.com\/vi\/lpg8Sp9RWi0\/maxresdefault.jpg",
                "mediaDuration": "65",
                "hdvFlag": 1,
                "uploadDate": 1300514953,
                "prettyDuration": "01:05"
            },
            "parentId": "158327",
            "url": "\/hurley\/brett-simpson-s-not-so-standard-three-to-the-beach\/158327-158716"
        },
        {
            "id": "158717",
            "title": "WAVE OF THE WEEK: AAMION GOODWIN",
            "date_created": "1398292506",
            "loginId": "3",
            "tags": "",
            "description": "This is one of those waves that gets passed along from friend to friend on facebook and email (it's so OMG). And it perfectly illustrates why Aamion is the r...",
            "asset": {
                "author": "Hurley",
                "videoId": "4WH2YmzjH4Y",
                "hookText": "This is one of those waves that gets passed along from friend to friend on facebook and email (it's so OMG). And it perfectly illustrates why Aamion is the r...",
                "thumbnailUrl": "https:\/\/i.ytimg.com\/vi\/4WH2YmzjH4Y\/maxresdefault.jpg",
                "mediaDuration": "36",
                "hdvFlag": 1,
                "uploadDate": 1300343974,
                "prettyDuration": "00:36"
            },
            "parentId": "158327",
            "url": "\/hurley\/wave-of-the-week-aamion-goodwin\/158327-158717"
        },
        {
            "id": "158718",
            "title": "OPENING NIGHT HIGHLIGHTS FROM INLE EXHIBIT AT GALLERY 1988",
            "date_created": "1398292506",
            "loginId": "3",
            "tags": "",
            "description": "Footage from the INLE opening at Gallery 1988. Video YB.",
            "asset": {
                "author": "Hurley",
                "videoId": "JVXMnBNveFs",
                "hookText": "Footage from the INLE opening at Gallery 1988. Video YB.",
                "thumbnailUrl": "https:\/\/i.ytimg.com\/vi\/JVXMnBNveFs\/maxresdefault.jpg",
                "mediaDuration": "165",
                "hdvFlag": 1,
                "uploadDate": 1300342856,
                "prettyDuration": "02:45"
            },
            "parentId": "158327",
            "url": "\/hurley\/opening-night-highlights-from-inle-exhibit-at-gallery-1988\/158327-158718"
        },
        {
            "id": "158719",
            "title": "WAVE OF THE WEEK: EVAN GEISELMAN",
            "date_created": "1398292507",
            "loginId": "3",
            "tags": "",
            "description": "Evan Geiselman shows that sometimes, dropping in, bottom turning and going straight can be the funnest thing to do on a surfboard. Video: Tom Aiello.",
            "asset": {
                "author": "Hurley",
                "videoId": "6WAQz1BMDvk",
                "hookText": "Evan Geiselman shows that sometimes, dropping in, bottom turning and going straight can be the funnest thing to do on a surfboard. Video: Tom Aiello.",
                "thumbnailUrl": "https:\/\/i.ytimg.com\/vi\/6WAQz1BMDvk\/maxresdefault.jpg",
                "mediaDuration": "30",
                "hdvFlag": 1,
                "uploadDate": 1299228139,
                "prettyDuration": "00:30"
            },
            "parentId": "158327",
            "url": "\/hurley\/wave-of-the-week-evan-geiselman\/158327-158719"
        }
    ]
}